{
  "video_id": "5Wu0PCEahsg",
  "title": "017 SIKKIM Stories",
  "description": "Documentary\nFacts and Fragments from the Himalayas.\ncamera: Jürg Da Vaz\nediting: Sándor Gréczi\ndirected by Jürg Da Vaz\nfilmed on site in Sikkim\na handmade Da Vaz production© 1999",
  "channel": "Jürg Davatz",
  "upload_date": "20130705",
  "duration_seconds": 1948,
  "width": 646,
  "height": 480,
  "fps": 25,
  "view_count": 84,
  "like_count": null,
  "categories": [
    "Education"
  ],
  "tags": [
    "Sikkim",
    "India",
    "Himalayas (Mountain Range)",
    "Gangtok"
  ],
  "thumbnail": "https://i.ytimg.com/vi/5Wu0PCEahsg/hqdefault.jpg?sqp=-oaymwEmCOADEOgC8quKqQMa8AEB-AGEBYAC4AOKAgwIABABGGUgTShRMA8=&rs=AOn4CLAxesljtVUnrQbObfcGSXc4yWiUHw",
  "webpage_url": "https://www.youtube.com/watch?v=5Wu0PCEahsg",
  "megapixels": 0.31,
  "definition": "sd",
  "scale": 4,
  "gpu": "RTX 4090",
  "resolution": "646x480"
}