{
  "video_id": "AjiFJbsRYyg",
  "title": "085a / 50 tons of wild life - Kenya",
  "description": "Kenya - Samburu National Reserve, 5 January 2001\n\"Get closer\", I told my driver. He got nervous. He said: \"Hyppos are the most dangerous animals in Africa. But I was glued to the river horses' eye. Bulls with females and their young... I try to keep cool. I was totally \"hyppotized\"... until my driver cut me off.",
  "channel": "Jürg Davatz",
  "upload_date": "20140331",
  "duration_seconds": 205,
  "width": 636,
  "height": 480,
  "fps": 25,
  "view_count": 179,
  "like_count": 1,
  "categories": [
    "Education"
  ],
  "tags": [
    "Kenya (Country)",
    "Life",
    "wild",
    "Deer",
    "Wildlife",
    "Privacy (Issue)",
    "Africa",
    "Elephant",
    "Lions",
    "Safari",
    "Samburu National Reserve (Protected Site)",
    "Tsavo East National Park (Protected Site)",
    "Leva Down",
    "National Park",
    "Baboon",
    "Nature",
    "Zebra",
    "Apes",
    "Crocodiles",
    "Giraffy",
    "Leopard",
    "Birds",
    "Gazelle",
    "oistrich"
  ],
  "thumbnail": "https://i.ytimg.com/vi/AjiFJbsRYyg/sddefault.jpg?sqp=-oaymwEmCIAFEOAD8quKqQMa8AEB-AH6BIAC4AOKAgwIABABGGUgZShlMA8=&rs=AOn4CLCI11X5OYt1t8JbpjogsLB3GZz2kg",
  "webpage_url": "https://www.youtube.com/watch?v=AjiFJbsRYyg",
  "megapixels": 0.31,
  "definition": "sd",
  "scale": 4,
  "gpu": "RTX 4090",
  "resolution": "636x480"
}