{
  "video_id": "mlPRxM0RY3E",
  "title": "Fundaziun Da Vaz – Ein Einblick",
  "description": "DIE FUNDAZIUN DA VAZ – Ein Einblick\nJürg Da Vaz im Interview mit Susanne Holthuizen",
  "channel": "Jürg Davatz",
  "upload_date": "20201021",
  "duration_seconds": 486,
  "width": 1920,
  "height": 1080,
  "fps": 50,
  "view_count": 471,
  "like_count": 6,
  "categories": [
    "Education"
  ],
  "tags": [],
  "thumbnail": "https://i.ytimg.com/vi/mlPRxM0RY3E/maxresdefault.jpg",
  "webpage_url": "https://www.youtube.com/watch?v=mlPRxM0RY3E",
  "megapixels": 2.07,
  "definition": "hd",
  "scale": 2,
  "gpu": "RTX 5090",
  "resolution": "1920x1080"
}